{
	"class" : {
		 },
	"instance" : {
		"fastListDragAndDrop" : "EstebanLorenzano 6/18/2015 16:03",
		"fastListDropDown" : "EstebanLorenzano 6/18/2015 16:06",
		"fastListFunctions" : "CyrilFerlicot 11/16/2015 11:44",
		"fastListOutlineSimple" : "usmanbhatti 10/13/2015 11:08",
		"fastListOutlineWithTag" : "CyrilFerlicot 11/9/2015 16:14",
		"fastListSimple" : "CyrilFerlicot 10/6/2015 15:37",
		"fastTableSimple" : "EstebanLorenzano 6/18/2015 12:04",
		"fastTableWithIcons" : "EstebanLorenzano 6/18/2015 12:04",
		"fastTableWithSearch" : "CyrilFerlicot 11/4/2015 16:13",
		"fastTreeSimple" : "CyrilFerlicot 11/10/2015 14:08",
		"fastTreeStrategies" : "CyrilFerlicot 11/10/2015 14:16",
		"fastTreeWithIcon" : "CyrilFerlicot 11/16/2015 10:04",
		"tagBlockWith:" : "CyrilFerlicot 11/10/2015 13:52" } }
